repo_to_single_page.py
rendergit-0.2.0.dist-info/METADATA
rendergit-0.2.0.dist-info/WHEEL
rendergit-0.2.0.dist-info/entry_points.txt
rendergit-0.2.0.dist-info/top_level.txt
rendergit-0.2.0.dist-info/RECORD
