Metadata-Version: 2.4
Name: rendergit
Version: 0.2.0
Summary: Flatten a GitHub repo into a single static HTML page for fast skimming and Ctrl+F
Author: Andrej Karpathy
Author-email: Eden Chan <edenchan717@gmail.com>
License: Apache-2.0
Project-URL: Homepage, https://github.com/eden-chan/rendergit
Project-URL: Repository, https://github.com/eden-chan/rendergit
Classifier: Development Status :: 4 - Beta
Classifier: Intended Audience :: Developers
Classifier: License :: OSI Approved :: Apache Software License
Classifier: Programming Language :: Python :: 3
Classifier: Programming Language :: Python :: 3.8
Classifier: Programming Language :: Python :: 3.9
Classifier: Programming Language :: Python :: 3.10
Classifier: Programming Language :: Python :: 3.11
Classifier: Programming Language :: Python :: 3.12
Requires-Python: >=3.8
Requires-Dist: pygments
Requires-Dist: markdown
